flickrsync/__init__.py
flickrsync/database.py
flickrsync/error.py
flickrsync/flickr.py
flickrsync/flickrsync.py
flickrsync/general.py
flickrsync/helpaction.py
flickrsync/local.py
flickrsync/log.py
flickrsync/settings.py
flickrsync/etc/__init__.py
flickrsync/etc/config.ini
flickrsync-0.1.1.data/scripts/flickrsync
flickrsync-0.1.1.dist-info/METADATA
flickrsync-0.1.1.dist-info/RECORD
flickrsync-0.1.1.dist-info/WHEEL
flickrsync-0.1.1.dist-info/top_level.txt
