Metadata-Version: 2.1
Name: flickrsync
Version: 0.1.1
Summary: A command line tool to synchronise pictures between the local file system and Flickr
Home-page: https://github.com/danchal/flickrsync
Author: Dan Chal
Author-email: UNKNOWN
License: GPL3
Keywords: flickr upload backup photo sync
Platform: UNKNOWN
Classifier: Development Status :: 5 - Production/Stable
Classifier: Environment :: Console
Classifier: Topic :: Utilities
Classifier: License :: OSI Approved :: GNU General Public License v3 or later (GPLv3+)
Classifier: Programming Language :: Python :: 3.4
Requires-Dist: Wand (>=0.4.4)
Requires-Dist: configparser
Requires-Dist: flickrapi (>=2.2.1)
